{
  "nome": "Marina Costa Alves",
  "titulo": "Desenvolvedora Full Stack Júnior",
  "email": "marina.alves@example.com",
  "telefone_e164": "+5511987654321",
  "telefone_exibicao": "(11) 98765-4321",
  "localizacao": "São Paulo, SP, Brasil",
  "linkedin_url": "https://www.linkedin.com/in/marina-costa-alves",
  "github_url": "https://github.com/marina-alves",
  "site_url": "https://marina-alves.dev",
  "resumo": "Dev full stack júnior. Atua com APIs Python/FastAPI e front-end React, testes com pytest/RTL e deploy simples em Docker. Busca vaga para seguir aprendendo arquitetura limpa e observabilidade.",
  "competencias_tecnicas": [
    { "grupo": "Programação e Desenvolvimento", "itens": ["Python", "Flask", "FastAPI", "JavaScript/TypeScript", "React", "HTML/CSS", "Git/GitHub", "pytest"] },
    { "grupo": "Banco de Dados", "itens": ["PostgreSQL", "SQLite", "Modelagem relacional", "ORM (SQLAlchemy)"] },
    { "grupo": "Sistemas Operacionais", "itens": ["Linux (Ubuntu/Debian)", "Windows 10/11"] }
  ],
  "competencias_comportamentais": ["Comunicação clara", "Curiosidade técnica", "Organização", "Colaboração em squad"],
  "diferenciais": ["Projetos pessoais publicados", "Documentação em inglês"],
  "projetos": [
    {
      "titulo": "AnalisaFrota API",
      "tecnologias": "Python, FastAPI, PostgreSQL, Docker",
      "pontos": [
        "API FastAPI para telemetria com alertas por e-mail",
        "JWT + testes pytest e pipeline CI/CD",
        "Containerização simples com Docker Compose"
      ],
      "links": [{ "rotulo": "Repositório", "url": "https://github.com/marina-alves/analisa-frota" }]
    }
  ],
  "experiencias": [
    {
      "cargo": "Estágio em Desenvolvimento Backend",
      "empresa": "Nuvem Verde Tech",
      "periodo": "2025.1 - 2025.2",
      "pontos": [
        "Endpoints Flask com SQLAlchemy e migrações Alembic",
        "Testes de integração e monitoramento básico",
        "Containerização de serviços para ambiente de staging"
      ]
    }
  ],
  "formacao": [
    { "titulo": "Bacharelado em Engenharia da Computação", "instituicao": "Universidade Estadual de Campinas (UNICAMP)", "periodo": "2023.1 - 2027.1" },
    { "titulo": "Técnico em Eletrônica", "instituicao": "SENAI-SP", "periodo": "2019 - 2021" }
  ],
  "cursos": [
    { "titulo": "Clean Code e TDD", "instituicao": "Udemy", "periodo": "2024" }
  ],
  "idiomas": [
    { "nome": "Português", "nivel": "Nativo", "observacao": "" },
    { "nome": "Inglês", "nivel": "Avançado", "observacao": "conversa e leitura técnica" }
  ],
  "ferramentas": ["Git e GitHub", "Postman / Insomnia", "Linux CLI", "VS Code"]
}
